async_elastic_logger/__init__.py
async_elastic_logger/logger.py
async_elastic_logger/logger_config.py
async_elastic_logger-0.4.5.1.4.dist-info/METADATA
async_elastic_logger-0.4.5.1.4.dist-info/WHEEL
async_elastic_logger-0.4.5.1.4.dist-info/top_level.txt
async_elastic_logger-0.4.5.1.4.dist-info/RECORD
