Metadata-Version: 2.1
Name: async_elastic_logger
Version: 0.4.5.1.4
Summary: A custom asynchronous logging library with Elasticsearch integration.
Home-page: https://github.com/nimamiri9248/async_elastic_logger
Author: Nima Miri
Author-email: nimamiri9248@gmail.com
License: MIT
Classifier: Intended Audience :: Developers
Classifier: License :: OSI Approved :: MIT License
Classifier: Programming Language :: Python :: 3.10
Classifier: Programming Language :: Python :: 3.11
Classifier: Programming Language :: Python :: 3.12
Classifier: Topic :: Software Development :: Libraries :: Python Modules
Classifier: Topic :: System :: Logging
Requires-Dist: pydantic==2.9.2
Requires-Dist: pydantic-settings==2.6.1
Requires-Dist: elasticsearch[async]==8.16.0
